robot_log_visualizer/__init__.py
robot_log_visualizer/__main__.py
robot_log_visualizer/plotter/__init__.py
robot_log_visualizer/plotter/color_palette.py
robot_log_visualizer/plotter/pyqtgraph_viewer_canvas.py
robot_log_visualizer/robot_visualizer/__init__.py
robot_log_visualizer/robot_visualizer/meshcat_provider.py
robot_log_visualizer/signal_provider/__init__.py
robot_log_visualizer/signal_provider/matfile_signal_provider.py
robot_log_visualizer/signal_provider/realtime_signal_provider.py
robot_log_visualizer/signal_provider/signal_provider.py
robot_log_visualizer/ui/__init__.py
robot_log_visualizer/ui/gui.py
robot_log_visualizer/ui/plot_item.py
robot_log_visualizer/ui/text_logging.py
robot_log_visualizer/ui/video_item.py
robot_log_visualizer/ui/autogenerated/__init__.py
robot_log_visualizer/ui/autogenerated/about.py
robot_log_visualizer/ui/autogenerated/plot_tab.py
robot_log_visualizer/ui/autogenerated/set_robot_model.py
robot_log_visualizer/ui/autogenerated/video_tab.py
robot_log_visualizer/ui/autogenerated/visualizer.py
robot_log_visualizer/ui/misc/__init__.py
robot_log_visualizer/ui/misc/about.ui
robot_log_visualizer/ui/misc/body-outline.svg
robot_log_visualizer/ui/misc/calendar-outline.svg
robot_log_visualizer/ui/misc/close-circle-outline.svg
robot_log_visualizer/ui/misc/document-text-outline.svg
robot_log_visualizer/ui/misc/folder-open-outline.svg
robot_log_visualizer/ui/misc/game-controller-outline.svg
robot_log_visualizer/ui/misc/icon.png
robot_log_visualizer/ui/misc/pause-outline.svg
robot_log_visualizer/ui/misc/play-outline.svg
robot_log_visualizer/ui/misc/plot_tab.ui
robot_log_visualizer/ui/misc/set_robot_model.ui
robot_log_visualizer/ui/misc/terminal-outline.svg
robot_log_visualizer/ui/misc/video_tab.ui
robot_log_visualizer/ui/misc/videocam-outline.svg
robot_log_visualizer/ui/misc/visualizer.ui
robot_log_visualizer/utils/__init__.py
robot_log_visualizer/utils/utils.py
robot_log_visualizer-0.12.0.dist-info/LICENSE
robot_log_visualizer-0.12.0.dist-info/METADATA
robot_log_visualizer-0.12.0.dist-info/WHEEL
robot_log_visualizer-0.12.0.dist-info/entry_points.txt
robot_log_visualizer-0.12.0.dist-info/top_level.txt
robot_log_visualizer-0.12.0.dist-info/RECORD
