Metadata-Version: 2.1
Name: robot-log-visualizer
Version: 0.12.0
Summary: Visualizer for robot logger
Home-page: https://github.com/ami-iit/robot-log-visualizer
Author: Giulio Romualdi
Author-email: giulio.romualdi@gmail.com
License: BSD3
Project-URL: Changelog, https://github.com/ami-iit/robot-log-visualizer/releases
Project-URL: Tracker, https://github.com/ami-iit/robot-log-visualizer/issues
Project-URL: Source, https://github.com/ami-iit/robot-log-visualizer
Keywords: robotics,visualization
Platform: any
Classifier: Development Status :: 4 - Beta
Classifier: Operating System :: OS Independent
Classifier: Topic :: Scientific/Engineering :: Visualization
Classifier: Topic :: Software Development
Classifier: Framework :: Robot Framework
Classifier: Intended Audience :: Developers
Classifier: Intended Audience :: Science/Research
Classifier: Programming Language :: Python :: 3.8
Classifier: Programming Language :: Python :: 3.9
Classifier: Programming Language :: Python :: 3.10
Classifier: Programming Language :: Python :: 3 :: Only
Requires-Python: >=3.8
License-File: LICENSE
Requires-Dist: idyntree>=10.2.0
Requires-Dist: meshcat
Requires-Dist: numpy
Requires-Dist: PyQt5
Requires-Dist: PyQtWebEngine
Requires-Dist: pyqtconsole
Requires-Dist: matplotlib
Requires-Dist: h5py
Requires-Dist: pyqtgraph
